<?xml version="1.0" encoding="UTF-8"?>
<tv generator-info-name="WebGrab+Plus/w MDB &amp; REX Postprocess -- version  V3.0.0.0 -- build 3 -- Jan van Straaten" generator-info-url="http://www.webgrabplus.com">
  <channel id="A+">
    <display-name lang="nl">A+</display-name>
    <url>http://www.yelotv.be</url>
  </channel>
  <channel id="Nollywood TV">
    <display-name lang="nl">Nollywood TV</display-name>
    <url>http://www.yelotv.be</url>
  </channel>
  <programme start="20200530035100 +0000" stop="20200530040500 +0000" channel="A+">
    <title lang="nl">Ma famille</title>
    <desc lang="nl">Le vécu de plusieurs familles ivoiriennes, entre palabres et ragots.(n)</desc>
    <credits>
      <actor>Michel Gohou</actor>
    </credits>
    <category lang="nl">eigentijds drama</category>
    <country lang="nl">CI</country>
  </programme>
  <programme start="20200530040500 +0000" stop="20200530042600 +0000" channel="A+">
    <title lang="nl">Sumu</title>
    <desc lang="nl">Série dramatique.(n)</desc>
    <category lang="nl">eigentijds drama</category>
  </programme>
  <programme start="20200530042600 +0000" stop="20200530044800 +0000" channel="A+">
    <title lang="nl">Sumu</title>
    <desc lang="nl">Série dramatique.(n)</desc>
    <category lang="nl">eigentijds drama</category>
  </programme>
  <programme start="20200530044800 +0000" stop="20200530051000 +0000" channel="A+">
    <title lang="nl">Sumu</title>
    <desc lang="nl">Série dramatique.(n)</desc>
    <category lang="nl">eigentijds drama</category>
  </programme>
  <programme start="20200530051000 +0000" stop="20200530053100 +0000" channel="A+">
    <title lang="nl">Sumu</title>
    <desc lang="nl">Série dramatique.(n)</desc>
    <category lang="nl">eigentijds drama</category>
  </programme>
  <programme start="20200530053100 +0000" stop="20200530055300 +0000" channel="A+">
    <title lang="nl">Sumu</title>
    <desc lang="nl">Série dramatique.(n)</desc>
    <category lang="nl">eigentijds drama</category>
  </programme>
  <programme start="20200530055300 +0000" stop="20200530061400 +0000" channel="A+">
    <title lang="nl">Sumu</title>
    <desc lang="nl">Série dramatique.(n)</desc>
    <category lang="nl">eigentijds drama</category>
  </programme>
  <programme start="20200530061400 +0000" stop="20200530063600 +0000" channel="A+">
    <title lang="nl">Sumu</title>
    <desc lang="nl">Série dramatique.(n)</desc>
    <category lang="nl">eigentijds drama</category>
  </programme>
  <programme start="20200530063600 +0000" stop="20200530070200 +0000" channel="A+">
    <title lang="nl">Sumu</title>
    <desc lang="nl">Série dramatique.(n)</desc>
    <category lang="nl">eigentijds drama</category>
  </programme>
  <programme start="20200530070200 +0000" stop="20200530071000 +0000" channel="A+">
    <title lang="nl">Mami Gbangban</title>
    <desc lang="nl">Divertissement.(n)</desc>
    <category lang="nl">Algemene non-fictie</category>
  </programme>
  <programme start="20200530071000 +0000" stop="20200530073500 +0000" channel="A+">
    <title lang="nl">Otages d'amour</title>
    <category lang="nl">eigentijds drama</category>
  </programme>
  <programme start="20200530073500 +0000" stop="20200530080200 +0000" channel="A+">
    <title lang="nl">Otages d'amour</title>
    <category lang="nl">eigentijds drama</category>
  </programme>
  <programme start="20200530080200 +0000" stop="20200530082700 +0000" channel="A+">
    <title lang="nl">Otages d'amour</title>
    <category lang="nl">eigentijds drama</category>
  </programme>
  <programme start="20200530082700 +0000" stop="20200530085300 +0000" channel="A+">
    <title lang="nl">Otages d'amour</title>
    <category lang="nl">eigentijds drama</category>
  </programme>
  <programme start="20200530085300 +0000" stop="20200530091900 +0000" channel="A+">
    <title lang="nl">Otages d'amour</title>
    <category lang="nl">eigentijds drama</category>
  </programme>
  <programme start="20200530091900 +0000" stop="20200530094300 +0000" channel="A+">
    <title lang="nl">Otages d'amour</title>
    <category lang="nl">eigentijds drama</category>
  </programme>
  <programme start="20200530094300 +0000" stop="20200530101000 +0000" channel="A+">
    <title lang="nl">Otages d'amour</title>
    <category lang="nl">eigentijds drama</category>
  </programme>
  <programme start="20200530101000 +0000" stop="20200530103600 +0000" channel="A+">
    <title lang="nl">Otages d'amour</title>
    <category lang="nl">eigentijds drama</category>
  </programme>
  <programme start="20200530103600 +0000" stop="20200530110500 +0000" channel="A+">
    <title lang="nl">Pod et Marichou</title>
    <category lang="nl">eigentijds drama</category>
    <country lang="nl">SN</country>
  </programme>
  <programme start="20200530110500 +0000" stop="20200530110900 +0000" channel="A+">
    <title lang="nl">L'heure africaine</title>
    <desc lang="nl">Decothey et ses amis croquent avec beaucoup d'humour la mauvaise habitude du retard.(n)</desc>
    <category lang="nl">Algemene non-fictie</category>
  </programme>
  <programme start="20200530110900 +0000" stop="20200530111200 +0000" channel="A+">
    <title lang="nl">L'heure africaine</title>
    <desc lang="nl">Decothey et ses amis croquent avec beaucoup d'humour la mauvaise habitude du retard.(n)</desc>
    <category lang="nl">Algemene non-fictie</category>
  </programme>
  <programme start="20200530111200 +0000" stop="20200530112000 +0000" channel="A+">
    <title lang="nl">L'heure africaine</title>
    <desc lang="nl">Decothey et ses amis croquent avec beaucoup d'humour la mauvaise habitude du retard.(n)</desc>
    <category lang="nl">Algemene non-fictie</category>
  </programme>
  <programme start="20200530112000 +0000" stop="20200530120100 +0000" channel="A+">
    <title lang="nl">La mélodie de l'amour</title>
    <category lang="nl">eigentijds drama</category>
  </programme>
  <programme start="20200530120100 +0000" stop="20200530124500 +0000" channel="A+">
    <title lang="nl">La mélodie de l'amour</title>
    <category lang="nl">eigentijds drama</category>
  </programme>
  <programme start="20200530124500 +0000" stop="20200530133000 +0000" channel="A+">
    <title lang="nl">Celia</title>
    <category lang="nl">eigentijds drama</category>
  </programme>
  <programme start="20200530133000 +0000" stop="20200530141600 +0000" channel="A+">
    <title lang="nl">Celia</title>
    <category lang="nl">eigentijds drama</category>
  </programme>
  <programme start="20200530141600 +0000" stop="20200530150000 +0000" channel="A+">
    <title lang="nl">Celia</title>
    <category lang="nl">eigentijds drama</category>
  </programme>
  <programme start="20200530150000 +0000" stop="20200530150600 +0000" channel="A+">
    <title lang="nl">Mami Gbangban</title>
    <desc lang="nl">Divertissement.(n)</desc>
    <category lang="nl">Algemene non-fictie</category>
  </programme>
  <programme start="20200530150600 +0000" stop="20200530151100 +0000" channel="A+">
    <title lang="nl">Mami Gbangban</title>
    <desc lang="nl">Divertissement.(n)</desc>
    <category lang="nl">Algemene non-fictie</category>
  </programme>
  <programme start="20200530151100 +0000" stop="20200530151500 +0000" channel="A+">
    <title lang="nl">Mami Gbangban</title>
    <desc lang="nl">Divertissement.(n)</desc>
    <category lang="nl">Algemene non-fictie</category>
  </programme>
  <programme start="20200530151500 +0000" stop="20200530152000 +0000" channel="A+">
    <title lang="nl">Mami Gbangban</title>
    <desc lang="nl">Divertissement.(n)</desc>
    <category lang="nl">Algemene non-fictie</category>
  </programme>
  <programme start="20200530152000 +0000" stop="20200530153000 +0000" channel="A+">
    <title lang="nl">Mami Gbangban</title>
    <desc lang="nl">Divertissement.(n)</desc>
    <category lang="nl">Algemene non-fictie</category>
  </programme>
  <programme start="20200530153000 +0000" stop="20200530155000 +0000" channel="A+">
    <title lang="nl">Sumu</title>
    <desc lang="nl">Série dramatique.(n)</desc>
    <category lang="nl">eigentijds drama</category>
  </programme>
  <programme start="20200530155000 +0000" stop="20200530161200 +0000" channel="A+">
    <title lang="nl">Sumu</title>
    <desc lang="nl">Série dramatique.(n)</desc>
    <category lang="nl">eigentijds drama</category>
  </programme>
  <programme start="20200530161200 +0000" stop="20200530163400 +0000" channel="A+">
    <title lang="nl">Sumu</title>
    <desc lang="nl">Série dramatique.(n)</desc>
    <category lang="nl">eigentijds drama</category>
  </programme>
  <programme start="20200530163400 +0000" stop="20200530165500 +0000" channel="A+">
    <title lang="nl">Sumu</title>
    <desc lang="nl">Série dramatique.(n)</desc>
    <category lang="nl">eigentijds drama</category>
  </programme>
  <programme start="20200530165500 +0000" stop="20200530171800 +0000" channel="A+">
    <title lang="nl">Sumu</title>
    <desc lang="nl">Série dramatique.(n)</desc>
    <category lang="nl">eigentijds drama</category>
  </programme>
  <programme start="20200530171800 +0000" stop="20200530173900 +0000" channel="A+">
    <title lang="nl">Sumu</title>
    <desc lang="nl">Série dramatique.(n)</desc>
    <category lang="nl">eigentijds drama</category>
  </programme>
  <programme start="20200530173900 +0000" stop="20200530180100 +0000" channel="A+">
    <title lang="nl">Sumu</title>
    <desc lang="nl">Série dramatique.(n)</desc>
    <category lang="nl">eigentijds drama</category>
  </programme>
  <programme start="20200530180100 +0000" stop="20200530182500 +0000" channel="A+">
    <title lang="nl">Sumu</title>
    <desc lang="nl">Série dramatique.(n)</desc>
    <category lang="nl">eigentijds drama</category>
  </programme>
  <programme start="20200530182500 +0000" stop="20200530183000 +0000" channel="A+">
    <title lang="nl">Clips</title>
    <sub-title lang="nl">Salsa Reggae</sub-title>
    <category lang="nl">Muziek</category>
    <icon src="https://cache.ps.yelo.prd.telenet-ops.be/yposter/images/MMImages/28454686.jpg" />
    <episode-num system="onscreen">E9999</episode-num>
  </programme>
  <programme start="20200530183000 +0000" stop="20200530185500 +0000" channel="A+">
    <title lang="nl">Otages d'amour</title>
    <category lang="nl">eigentijds drama</category>
  </programme>
  <programme start="20200530185500 +0000" stop="20200530192200 +0000" channel="A+">
    <title lang="nl">Otages d'amour</title>
    <category lang="nl">eigentijds drama</category>
  </programme>
  <programme start="20200530192200 +0000" stop="20200530194700 +0000" channel="A+">
    <title lang="nl">Otages d'amour</title>
    <category lang="nl">eigentijds drama</category>
  </programme>
  <programme start="20200530194700 +0000" stop="20200530201300 +0000" channel="A+">
    <title lang="nl">Otages d'amour</title>
    <category lang="nl">eigentijds drama</category>
  </programme>
  <programme start="20200530201300 +0000" stop="20200530203900 +0000" channel="A+">
    <title lang="nl">Otages d'amour</title>
    <category lang="nl">eigentijds drama</category>
  </programme>
  <programme start="20200530203900 +0000" stop="20200530210300 +0000" channel="A+">
    <title lang="nl">Otages d'amour</title>
    <category lang="nl">eigentijds drama</category>
  </programme>
  <programme start="20200530210300 +0000" stop="20200530213000 +0000" channel="A+">
    <title lang="nl">Otages d'amour</title>
    <category lang="nl">eigentijds drama</category>
  </programme>
  <programme start="20200530213000 +0000" stop="20200530215400 +0000" channel="A+">
    <title lang="nl">Otages d'amour</title>
    <category lang="nl">eigentijds drama</category>
  </programme>
  <programme start="20200530215400 +0000" stop="20200530222400 +0000" channel="A+">
    <title lang="nl">Pod et Marichou</title>
    <category lang="nl">eigentijds drama</category>
    <country lang="nl">SN</country>
  </programme>
  <programme start="20200530222400 +0000" stop="20200530224500 +0000" channel="A+">
    <title lang="nl">Ma famille</title>
    <desc lang="nl">Le vécu de plusieurs familles ivoiriennes, entre palabres et ragots.(n)</desc>
    <credits>
      <actor>Michel Gohou</actor>
    </credits>
    <category lang="nl">eigentijds drama</category>
    <country lang="nl">CI</country>
  </programme>
  <programme start="20200530224500 +0000" stop="20200530230700 +0000" channel="A+">
    <title lang="nl">Ma famille</title>
    <desc lang="nl">Le vécu de plusieurs familles ivoiriennes, entre palabres et ragots.(n)</desc>
    <credits>
      <actor>Michel Gohou</actor>
    </credits>
    <category lang="nl">eigentijds drama</category>
    <country lang="nl">CI</country>
  </programme>
  <programme start="20200530230700 +0000" stop="20200530233200 +0000" channel="A+">
    <title lang="nl">Ma famille</title>
    <desc lang="nl">Le vécu de plusieurs familles ivoiriennes, entre palabres et ragots.(n)</desc>
    <credits>
      <actor>Michel Gohou</actor>
    </credits>
    <category lang="nl">eigentijds drama</category>
    <country lang="nl">CI</country>
  </programme>
  <programme start="20200530233200 +0000" stop="20200530235900 +0000" channel="A+">
    <title lang="nl">Ma famille</title>
    <desc lang="nl">Le vécu de plusieurs familles ivoiriennes, entre palabres et ragots.(n)</desc>
    <credits>
      <actor>Michel Gohou</actor>
    </credits>
    <category lang="nl">eigentijds drama</category>
    <country lang="nl">CI</country>
  </programme>
  <programme start="20200530235900 +0000" stop="20200531002700 +0000" channel="A+">
    <title lang="nl">Ma famille</title>
    <desc lang="nl">Le vécu de plusieurs familles ivoiriennes, entre palabres et ragots.(n)</desc>
    <credits>
      <actor>Michel Gohou</actor>
    </credits>
    <category lang="nl">eigentijds drama</category>
    <country lang="nl">CI</country>
  </programme>
  <programme start="20200531002700 +0000" stop="20200531005500 +0000" channel="A+">
    <title lang="nl">Ma famille</title>
    <desc lang="nl">Le vécu de plusieurs familles ivoiriennes, entre palabres et ragots.(n)</desc>
    <credits>
      <actor>Michel Gohou</actor>
    </credits>
    <category lang="nl">eigentijds drama</category>
    <country lang="nl">CI</country>
  </programme>
  <programme start="20200531005500 +0000" stop="20200531012200 +0000" channel="A+">
    <title lang="nl">Ma famille</title>
    <desc lang="nl">Le vécu de plusieurs familles ivoiriennes, entre palabres et ragots.(n)</desc>
    <credits>
      <actor>Michel Gohou</actor>
    </credits>
    <category lang="nl">eigentijds drama</category>
    <country lang="nl">CI</country>
  </programme>
  <programme start="20200531012200 +0000" stop="20200531014500 +0000" channel="A+">
    <title lang="nl">Ma famille</title>
    <desc lang="nl">Le vécu de plusieurs familles ivoiriennes, entre palabres et ragots.(n)</desc>
    <credits>
      <actor>Michel Gohou</actor>
    </credits>
    <category lang="nl">eigentijds drama</category>
    <country lang="nl">CI</country>
  </programme>
  <programme start="20200531014500 +0000" stop="20200531020700 +0000" channel="A+">
    <title lang="nl">Ma famille</title>
    <desc lang="nl">Le vécu de plusieurs familles ivoiriennes, entre palabres et ragots.(n)</desc>
    <credits>
      <actor>Michel Gohou</actor>
    </credits>
    <category lang="nl">eigentijds drama</category>
    <country lang="nl">CI</country>
  </programme>
  <programme start="20200531020700 +0000" stop="20200531023000 +0000" channel="A+">
    <title lang="nl">Ma famille</title>
    <desc lang="nl">Le vécu de plusieurs familles ivoiriennes, entre palabres et ragots.(n)</desc>
    <credits>
      <actor>Michel Gohou</actor>
    </credits>
    <category lang="nl">eigentijds drama</category>
    <country lang="nl">CI</country>
  </programme>
  <programme start="20200531023000 +0000" stop="20200531025100 +0000" channel="A+">
    <title lang="nl">Ma famille</title>
    <desc lang="nl">Le vécu de plusieurs familles ivoiriennes, entre palabres et ragots.(n)</desc>
    <credits>
      <actor>Michel Gohou</actor>
    </credits>
    <category lang="nl">eigentijds drama</category>
    <country lang="nl">CI</country>
  </programme>
  <programme start="20200531025100 +0000" stop="20200531030000 +0000" channel="A+">
    <title lang="nl">Mami Gbangban</title>
    <desc lang="nl">Divertissement.(n)</desc>
    <category lang="nl">Algemene non-fictie</category>
  </programme>
  <programme start="20200531030000 +0000" stop="20200531032100 +0000" channel="A+">
    <title lang="nl">Sumu</title>
    <desc lang="nl">Série dramatique.(n)</desc>
    <category lang="nl">eigentijds drama</category>
  </programme>
  <programme start="20200531032100 +0000" stop="20200531034400 +0000" channel="A+">
    <title lang="nl">Sumu</title>
    <desc lang="nl">Série dramatique.(n)</desc>
    <category lang="nl">eigentijds drama</category>
  </programme>
  <programme start="20200531034400 +0000" stop="20200531042400 +0000" channel="A+">
    <title lang="nl">Sumu</title>
    <desc lang="nl">Série dramatique.(n)</desc>
    <category lang="nl">eigentijds drama</category>
  </programme>
  <programme start="20200531042400 +0000" stop="20200531050900 +0000" channel="A+">
    <title lang="nl">Celia</title>
    <category lang="nl">eigentijds drama</category>
  </programme>
  <programme start="20200531050900 +0000" stop="20200531055500 +0000" channel="A+">
    <title lang="nl">Celia</title>
    <category lang="nl">eigentijds drama</category>
  </programme>
  <programme start="20200531055500 +0000" stop="20200531064000 +0000" channel="A+">
    <title lang="nl">Celia</title>
    <category lang="nl">eigentijds drama</category>
  </programme>
  <programme start="20200531064000 +0000" stop="20200531064600 +0000" channel="A+">
    <title lang="nl">Mami Gbangban</title>
    <desc lang="nl">Divertissement.(n)</desc>
    <category lang="nl">Algemene non-fictie</category>
  </programme>
  <programme start="20200531064600 +0000" stop="20200531065100 +0000" channel="A+">
    <title lang="nl">Mami Gbangban</title>
    <desc lang="nl">Divertissement.(n)</desc>
    <category lang="nl">Algemene non-fictie</category>
  </programme>
  <programme start="20200531065100 +0000" stop="20200531065500 +0000" channel="A+">
    <title lang="nl">Mami Gbangban</title>
    <desc lang="nl">Divertissement.(n)</desc>
    <category lang="nl">Algemene non-fictie</category>
  </programme>
  <programme start="20200531065500 +0000" stop="20200531070000 +0000" channel="A+">
    <title lang="nl">Mami Gbangban</title>
    <desc lang="nl">Divertissement.(n)</desc>
    <category lang="nl">Algemene non-fictie</category>
  </programme>
  <programme start="20200531070000 +0000" stop="20200531071000 +0000" channel="A+">
    <title lang="nl">Mami Gbangban</title>
    <desc lang="nl">Divertissement.(n)</desc>
    <category lang="nl">Algemene non-fictie</category>
  </programme>
  <programme start="20200531071000 +0000" stop="20200531073200 +0000" channel="A+">
    <title lang="nl">Ma famille</title>
    <desc lang="nl">Le vécu de plusieurs familles ivoiriennes, entre palabres et ragots.(n)</desc>
    <credits>
      <actor>Michel Gohou</actor>
    </credits>
    <category lang="nl">eigentijds drama</category>
    <country lang="nl">CI</country>
  </programme>
  <programme start="20200531073200 +0000" stop="20200531075700 +0000" channel="A+">
    <title lang="nl">Ma famille</title>
    <desc lang="nl">Le vécu de plusieurs familles ivoiriennes, entre palabres et ragots.(n)</desc>
    <credits>
      <actor>Michel Gohou</actor>
    </credits>
    <category lang="nl">eigentijds drama</category>
    <country lang="nl">CI</country>
  </programme>
  <programme start="20200531075700 +0000" stop="20200531082400 +0000" channel="A+">
    <title lang="nl">Ma famille</title>
    <desc lang="nl">Le vécu de plusieurs familles ivoiriennes, entre palabres et ragots.(n)</desc>
    <credits>
      <actor>Michel Gohou</actor>
    </credits>
    <category lang="nl">eigentijds drama</category>
    <country lang="nl">CI</country>
  </programme>
  <programme start="20200531082400 +0000" stop="20200531085200 +0000" channel="A+">
    <title lang="nl">Ma famille</title>
    <desc lang="nl">Le vécu de plusieurs familles ivoiriennes, entre palabres et ragots.(n)</desc>
    <credits>
      <actor>Michel Gohou</actor>
    </credits>
    <category lang="nl">eigentijds drama</category>
    <country lang="nl">CI</country>
  </programme>
  <programme start="20200531085200 +0000" stop="20200531092000 +0000" channel="A+">
    <title lang="nl">Ma famille</title>
    <desc lang="nl">Le vécu de plusieurs familles ivoiriennes, entre palabres et ragots.(n)</desc>
    <credits>
      <actor>Michel Gohou</actor>
    </credits>
    <category lang="nl">eigentijds drama</category>
    <country lang="nl">CI</country>
  </programme>
  <programme start="20200531092000 +0000" stop="20200531094700 +0000" channel="A+">
    <title lang="nl">Ma famille</title>
    <desc lang="nl">Le vécu de plusieurs familles ivoiriennes, entre palabres et ragots.(n)</desc>
    <credits>
      <actor>Michel Gohou</actor>
    </credits>
    <category lang="nl">eigentijds drama</category>
    <country lang="nl">CI</country>
  </programme>
  <programme start="20200531094700 +0000" stop="20200531101000 +0000" channel="A+">
    <title lang="nl">Ma famille</title>
    <desc lang="nl">Le vécu de plusieurs familles ivoiriennes, entre palabres et ragots.(n)</desc>
    <credits>
      <actor>Michel Gohou</actor>
    </credits>
    <category lang="nl">eigentijds drama</category>
    <country lang="nl">CI</country>
  </programme>
  <programme start="20200531101000 +0000" stop="20200531103200 +0000" channel="A+">
    <title lang="nl">Ma famille</title>
    <desc lang="nl">Le vécu de plusieurs familles ivoiriennes, entre palabres et ragots.(n)</desc>
    <credits>
      <actor>Michel Gohou</actor>
    </credits>
    <category lang="nl">eigentijds drama</category>
    <country lang="nl">CI</country>
  </programme>
  <programme start="20200531103200 +0000" stop="20200531105500 +0000" channel="A+">
    <title lang="nl">Ma famille</title>
    <desc lang="nl">Le vécu de plusieurs familles ivoiriennes, entre palabres et ragots.(n)</desc>
    <credits>
      <actor>Michel Gohou</actor>
    </credits>
    <category lang="nl">eigentijds drama</category>
    <country lang="nl">CI</country>
  </programme>
  <programme start="20200531105500 +0000" stop="20200531112000 +0000" channel="A+">
    <title lang="nl">Ma famille</title>
    <desc lang="nl">Le vécu de plusieurs familles ivoiriennes, entre palabres et ragots.(n)</desc>
    <credits>
      <actor>Michel Gohou</actor>
    </credits>
    <category lang="nl">eigentijds drama</category>
    <country lang="nl">CI</country>
  </programme>
  <programme start="20200531112000 +0000" stop="20200531114100 +0000" channel="A+">
    <title lang="nl">Sumu</title>
    <desc lang="nl">Série dramatique.(n)</desc>
    <category lang="nl">eigentijds drama</category>
  </programme>
  <programme start="20200531114100 +0000" stop="20200531120400 +0000" channel="A+">
    <title lang="nl">Sumu</title>
    <desc lang="nl">Série dramatique.(n)</desc>
    <category lang="nl">eigentijds drama</category>
  </programme>
  <programme start="20200531120400 +0000" stop="20200531122500 +0000" channel="A+">
    <title lang="nl">Sumu</title>
    <desc lang="nl">Série dramatique.(n)</desc>
    <category lang="nl">eigentijds drama</category>
  </programme>
  <programme start="20200531122500 +0000" stop="20200531124500 +0000" channel="A+">
    <title lang="nl">Sumu</title>
    <desc lang="nl">Série dramatique.(n)</desc>
    <category lang="nl">eigentijds drama</category>
  </programme>
  <programme start="20200531124500 +0000" stop="20200531130700 +0000" channel="A+">
    <title lang="nl">Sumu</title>
    <desc lang="nl">Série dramatique.(n)</desc>
    <category lang="nl">eigentijds drama</category>
  </programme>
  <programme start="20200531130700 +0000" stop="20200531132900 +0000" channel="A+">
    <title lang="nl">Sumu</title>
    <desc lang="nl">Série dramatique.(n)</desc>
    <category lang="nl">eigentijds drama</category>
  </programme>
  <programme start="20200531132900 +0000" stop="20200531135000 +0000" channel="A+">
    <title lang="nl">Sumu</title>
    <desc lang="nl">Série dramatique.(n)</desc>
    <category lang="nl">eigentijds drama</category>
  </programme>
  <programme start="20200531135000 +0000" stop="20200531141300 +0000" channel="A+">
    <title lang="nl">Sumu</title>
    <desc lang="nl">Série dramatique.(n)</desc>
    <category lang="nl">eigentijds drama</category>
  </programme>
  <programme start="20200531141300 +0000" stop="20200531143400 +0000" channel="A+">
    <title lang="nl">Sumu</title>
    <desc lang="nl">Série dramatique.(n)</desc>
    <category lang="nl">eigentijds drama</category>
  </programme>
  <programme start="20200531143400 +0000" stop="20200531145600 +0000" channel="A+">
    <title lang="nl">Sumu</title>
    <desc lang="nl">Série dramatique.(n)</desc>
    <category lang="nl">eigentijds drama</category>
  </programme>
  <programme start="20200531145600 +0000" stop="20200531152100 +0000" channel="A+">
    <title lang="nl">Sumu</title>
    <desc lang="nl">Série dramatique.(n)</desc>
    <category lang="nl">eigentijds drama</category>
  </programme>
  <programme start="20200531152100 +0000" stop="20200531152300 +0000" channel="A+">
    <title lang="nl">L'heure africaine</title>
    <desc lang="nl">Decothey et ses amis croquent avec beaucoup d'humour la mauvaise habitude du retard.(n)</desc>
    <category lang="nl">Algemene non-fictie</category>
  </programme>
  <programme start="20200531152300 +0000" stop="20200531153000 +0000" channel="A+">
    <title lang="nl">L'heure africaine</title>
    <desc lang="nl">Decothey et ses amis croquent avec beaucoup d'humour la mauvaise habitude du retard.(n)</desc>
    <category lang="nl">Algemene non-fictie</category>
  </programme>
  <programme start="20200531153000 +0000" stop="20200531155500 +0000" channel="A+">
    <title lang="nl">Otages d'amour</title>
    <category lang="nl">eigentijds drama</category>
  </programme>
  <programme start="20200531155500 +0000" stop="20200531162000 +0000" channel="A+">
    <title lang="nl">Otages d'amour</title>
    <category lang="nl">eigentijds drama</category>
  </programme>
  <programme start="20200531162000 +0000" stop="20200531164700 +0000" channel="A+">
    <title lang="nl">Otages d'amour</title>
    <category lang="nl">eigentijds drama</category>
  </programme>
  <programme start="20200531164700 +0000" stop="20200531171100 +0000" channel="A+">
    <title lang="nl">Otages d'amour</title>
    <category lang="nl">eigentijds drama</category>
  </programme>
  <programme start="20200531171100 +0000" stop="20200531173800 +0000" channel="A+">
    <title lang="nl">Otages d'amour</title>
    <category lang="nl">eigentijds drama</category>
  </programme>
  <programme start="20200531173800 +0000" stop="20200531180200 +0000" channel="A+">
    <title lang="nl">Otages d'amour</title>
    <category lang="nl">eigentijds drama</category>
  </programme>
  <programme start="20200531180200 +0000" stop="20200531183000 +0000" channel="A+">
    <title lang="nl">Pod et Marichou</title>
    <category lang="nl">eigentijds drama</category>
    <country lang="nl">SN</country>
  </programme>
  <programme start="20200531183000 +0000" stop="20200531191100 +0000" channel="A+">
    <title lang="nl">La mélodie de l'amour</title>
    <category lang="nl">eigentijds drama</category>
  </programme>
  <programme start="20200531191100 +0000" stop="20200531195300 +0000" channel="A+">
    <title lang="nl">La mélodie de l'amour</title>
    <category lang="nl">eigentijds drama</category>
  </programme>
  <programme start="20200531195300 +0000" stop="20200531203900 +0000" channel="A+">
    <title lang="nl">Celia</title>
    <category lang="nl">eigentijds drama</category>
  </programme>
  <programme start="20200531203900 +0000" stop="20200531212400 +0000" channel="A+">
    <title lang="nl">Celia</title>
    <category lang="nl">eigentijds drama</category>
  </programme>
  <programme start="20200531212400 +0000" stop="20200531220900 +0000" channel="A+">
    <title lang="nl">Celia</title>
    <category lang="nl">eigentijds drama</category>
  </programme>
  <programme start="20200531220900 +0000" stop="20200531221300 +0000" channel="A+">
    <title lang="nl">Clips</title>
    <sub-title lang="nl">Salsa Reggae</sub-title>
    <category lang="nl">Muziek</category>
    <icon src="https://cache.ps.yelo.prd.telenet-ops.be/yposter/images/MMImages/28454686.jpg" />
    <episode-num system="onscreen">E9999</episode-num>
  </programme>
  <programme start="20200531221300 +0000" stop="20200531223400 +0000" channel="A+">
    <title lang="nl">Sumu</title>
    <desc lang="nl">Série dramatique.(n)</desc>
    <category lang="nl">eigentijds drama</category>
  </programme>
  <programme start="20200531223400 +0000" stop="20200531225700 +0000" channel="A+">
    <title lang="nl">Sumu</title>
    <desc lang="nl">Série dramatique.(n)</desc>
    <category lang="nl">eigentijds drama</category>
  </programme>
  <programme start="20200531225700 +0000" stop="20200531231800 +0000" channel="A+">
    <title lang="nl">Sumu</title>
    <desc lang="nl">Série dramatique.(n)</desc>
    <category lang="nl">eigentijds drama</category>
  </programme>
  <programme start="20200531231800 +0000" stop="20200531234000 +0000" channel="A+">
    <title lang="nl">Sumu</title>
    <desc lang="nl">Série dramatique.(n)</desc>
    <category lang="nl">eigentijds drama</category>
  </programme>
  <programme start="20200531234000 +0000" stop="20200601000100 +0000" channel="A+">
    <title lang="nl">Sumu</title>
    <desc lang="nl">Série dramatique.(n)</desc>
    <category lang="nl">eigentijds drama</category>
  </programme>
  <programme start="20200601000100 +0000" stop="20200601002300 +0000" channel="A+">
    <title lang="nl">Sumu</title>
    <desc lang="nl">Série dramatique.(n)</desc>
    <category lang="nl">eigentijds drama</category>
  </programme>
  <programme start="20200601002300 +0000" stop="20200601004400 +0000" channel="A+">
    <title lang="nl">Sumu</title>
    <desc lang="nl">Série dramatique.(n)</desc>
    <category lang="nl">eigentijds drama</category>
  </programme>
  <programme start="20200601004400 +0000" stop="20200601010600 +0000" channel="A+">
    <title lang="nl">Sumu</title>
    <desc lang="nl">Série dramatique.(n)</desc>
    <category lang="nl">eigentijds drama</category>
  </programme>
  <programme start="20200601010600 +0000" stop="20200601012700 +0000" channel="A+">
    <title lang="nl">Sumu</title>
    <desc lang="nl">Série dramatique.(n)</desc>
    <category lang="nl">eigentijds drama</category>
  </programme>
  <programme start="20200601012700 +0000" stop="20200601014900 +0000" channel="A+">
    <title lang="nl">Sumu</title>
    <desc lang="nl">Série dramatique.(n)</desc>
    <category lang="nl">eigentijds drama</category>
  </programme>
  <programme start="20200601014900 +0000" stop="20200601021300 +0000" channel="A+">
    <title lang="nl">Sumu</title>
    <desc lang="nl">Série dramatique.(n)</desc>
    <category lang="nl">eigentijds drama</category>
  </programme>
  <programme start="20200601021300 +0000" stop="20200601021900 +0000" channel="A+">
    <title lang="nl">Mami Gbangban</title>
    <desc lang="nl">Divertissement.(n)</desc>
    <category lang="nl">Algemene non-fictie</category>
  </programme>
  <programme start="20200601021900 +0000" stop="20200601022400 +0000" channel="A+">
    <title lang="nl">Mami Gbangban</title>
    <desc lang="nl">Divertissement.(n)</desc>
    <category lang="nl">Algemene non-fictie</category>
  </programme>
  <programme start="20200601022400 +0000" stop="20200601022800 +0000" channel="A+">
    <title lang="nl">Mami Gbangban</title>
    <desc lang="nl">Divertissement.(n)</desc>
    <category lang="nl">Algemene non-fictie</category>
  </programme>
  <programme start="20200601022800 +0000" stop="20200601023300 +0000" channel="A+">
    <title lang="nl">Mami Gbangban</title>
    <desc lang="nl">Divertissement.(n)</desc>
    <category lang="nl">Algemene non-fictie</category>
  </programme>
  <programme start="20200601023300 +0000" stop="20200601023800 +0000" channel="A+">
    <title lang="nl">Mami Gbangban</title>
    <desc lang="nl">Divertissement.(n)</desc>
    <category lang="nl">Algemene non-fictie</category>
  </programme>
  <programme start="20200601023800 +0000" stop="20200601024300 +0000" channel="A+">
    <title lang="nl">L'heure africaine</title>
    <desc lang="nl">Decothey et ses amis croquent avec beaucoup d'humour la mauvaise habitude du retard.(n)</desc>
    <category lang="nl">Algemene non-fictie</category>
  </programme>
  <programme start="20200601024300 +0000" stop="20200601024600 +0000" channel="A+">
    <title lang="nl">L'heure africaine</title>
    <desc lang="nl">Decothey et ses amis croquent avec beaucoup d'humour la mauvaise habitude du retard.(n)</desc>
    <category lang="nl">Algemene non-fictie</category>
  </programme>
  <programme start="20200601024600 +0000" stop="20200601030000 +0000" channel="A+">
    <title lang="nl">L'heure africaine</title>
    <desc lang="nl">Decothey et ses amis croquent avec beaucoup d'humour la mauvaise habitude du retard.(n)</desc>
    <category lang="nl">Algemene non-fictie</category>
  </programme>
  <programme start="20200601030000 +0000" stop="20200601034200 +0000" channel="A+">
    <title lang="nl">La mélodie de l'amour</title>
    <category lang="nl">eigentijds drama</category>
  </programme>
  <programme start="20200601034200 +0000" stop="20200601041500 +0000" channel="A+">
    <title lang="nl">La mélodie de l'amour</title>
    <category lang="nl">eigentijds drama</category>
  </programme>
  <programme start="20200601041500 +0000" stop="20200601043600 +0000" channel="A+">
    <title lang="nl">Ma famille</title>
    <desc lang="nl">Le vécu de plusieurs familles ivoiriennes, entre palabres et ragots.(n)</desc>
    <credits>
      <actor>Michel Gohou</actor>
    </credits>
    <category lang="nl">eigentijds drama</category>
    <country lang="nl">CI</country>
  </programme>
  <programme start="20200601043600 +0000" stop="20200601052000 +0000" channel="A+">
    <title lang="nl">Celia</title>
    <category lang="nl">eigentijds drama</category>
  </programme>
  <programme start="20200601052000 +0000" stop="20200601052600 +0000" channel="A+">
    <title lang="nl">Mami Gbangban</title>
    <desc lang="nl">Divertissement.(n)</desc>
    <category lang="nl">Algemene non-fictie</category>
  </programme>
  <programme start="20200601052600 +0000" stop="20200601053300 +0000" channel="A+">
    <title lang="nl">Mami Gbangban</title>
    <desc lang="nl">Divertissement.(n)</desc>
    <category lang="nl">Algemene non-fictie</category>
  </programme>
  <programme start="20200601053300 +0000" stop="20200601055500 +0000" channel="A+">
    <title lang="nl">Sumu</title>
    <desc lang="nl">Série dramatique.(n)</desc>
    <category lang="nl">eigentijds drama</category>
  </programme>
  <programme start="20200601055500 +0000" stop="20200601062000 +0000" channel="A+">
    <title lang="nl">Sumu</title>
    <desc lang="nl">Série dramatique.(n)</desc>
    <category lang="nl">eigentijds drama</category>
  </programme>
  <programme start="20200601062000 +0000" stop="20200601064400 +0000" channel="A+">
    <title lang="nl">Otages d'amour</title>
    <category lang="nl">eigentijds drama</category>
  </programme>
  <programme start="20200601064400 +0000" stop="20200601071300 +0000" channel="A+">
    <title lang="nl">Pod et Marichou</title>
    <category lang="nl">eigentijds drama</category>
    <country lang="nl">SN</country>
  </programme>
  <programme start="20200601071300 +0000" stop="20200601073500 +0000" channel="A+">
    <title lang="nl">Ma famille</title>
    <desc lang="nl">Le vécu de plusieurs familles ivoiriennes, entre palabres et ragots.(n)</desc>
    <credits>
      <actor>Michel Gohou</actor>
    </credits>
    <category lang="nl">eigentijds drama</category>
    <country lang="nl">CI</country>
  </programme>
  <programme start="20200601073500 +0000" stop="20200601075700 +0000" channel="A+">
    <title lang="nl">Ma famille</title>
    <desc lang="nl">Le vécu de plusieurs familles ivoiriennes, entre palabres et ragots.(n)</desc>
    <credits>
      <actor>Michel Gohou</actor>
    </credits>
    <category lang="nl">eigentijds drama</category>
    <country lang="nl">CI</country>
  </programme>
  <programme start="20200601075700 +0000" stop="20200601080100 +0000" channel="A+">
    <title lang="nl">L'heure africaine</title>
    <desc lang="nl">Decothey et ses amis croquent avec beaucoup d'humour la mauvaise habitude du retard.(n)</desc>
    <category lang="nl">Algemene non-fictie</category>
  </programme>
  <programme start="20200601080100 +0000" stop="20200601085000 +0000" channel="A+">
    <title lang="nl">Celia</title>
    <category lang="nl">eigentijds drama</category>
  </programme>
  <programme start="20200601085000 +0000" stop="20200601091200 +0000" channel="A+">
    <title lang="nl">Sumu</title>
    <desc lang="nl">Série dramatique.(n)</desc>
    <category lang="nl">eigentijds drama</category>
  </programme>
  <programme start="20200601091200 +0000" stop="20200601093500 +0000" channel="A+">
    <title lang="nl">Sumu</title>
    <desc lang="nl">Série dramatique.(n)</desc>
    <category lang="nl">eigentijds drama</category>
  </programme>
  <programme start="20200601093500 +0000" stop="20200601095900 +0000" channel="A+">
    <title lang="nl">Otages d'amour</title>
    <category lang="nl">eigentijds drama</category>
  </programme>
  <programme start="20200601095900 +0000" stop="20200601102800 +0000" channel="A+">
    <title lang="nl">Pod et Marichou</title>
    <category lang="nl">eigentijds drama</category>
    <country lang="nl">SN</country>
  </programme>
  <programme start="20200601102800 +0000" stop="20200601105100 +0000" channel="A+">
    <title lang="nl">Ma famille</title>
    <desc lang="nl">Le vécu de plusieurs familles ivoiriennes, entre palabres et ragots.(n)</desc>
    <credits>
      <actor>Michel Gohou</actor>
    </credits>
    <category lang="nl">eigentijds drama</category>
    <country lang="nl">CI</country>
  </programme>
  <programme start="20200601105100 +0000" stop="20200601111400 +0000" channel="A+">
    <title lang="nl">Ma famille</title>
    <desc lang="nl">Le vécu de plusieurs familles ivoiriennes, entre palabres et ragots.(n)</desc>
    <credits>
      <actor>Michel Gohou</actor>
    </credits>
    <category lang="nl">eigentijds drama</category>
    <country lang="nl">CI</country>
  </programme>
  <programme start="20200601111400 +0000" stop="20200601115800 +0000" channel="A+">
    <title lang="nl">Celia</title>
    <category lang="nl">eigentijds drama</category>
  </programme>
  <programme start="20200601115800 +0000" stop="20200601120100 +0000" channel="A+">
    <title lang="nl">Clips</title>
    <sub-title lang="nl">Pas fatigue</sub-title>
    <category lang="nl">Muziek</category>
    <icon src="https://cache.ps.yelo.prd.telenet-ops.be/yposter/images/MMImages/28454686.jpg" />
    <episode-num system="onscreen">E9999</episode-num>
  </programme>
  <programme start="20200601120100 +0000" stop="20200601120700 +0000" channel="A+">
    <title lang="nl">Mami Gbangban</title>
    <desc lang="nl">Divertissement.(n)</desc>
    <category lang="nl">Algemene non-fictie</category>
  </programme>
  <programme start="20200601120700 +0000" stop="20200601123000 +0000" channel="A+">
    <title lang="nl">Sumu</title>
    <desc lang="nl">Série dramatique.(n)</desc>
    <category lang="nl">eigentijds drama</category>
  </programme>
  <programme start="20200601123000 +0000" stop="20200601130000 +0000" channel="A+">
    <title lang="nl">Sumu</title>
    <desc lang="nl">Série dramatique.(n)</desc>
    <category lang="nl">eigentijds drama</category>
  </programme>
  <programme start="20200601130000 +0000" stop="20200601132500 +0000" channel="A+">
    <title lang="nl">Pod et Marichou</title>
    <category lang="nl">eigentijds drama</category>
    <country lang="nl">SN</country>
  </programme>
  <programme start="20200601132500 +0000" stop="20200601140100 +0000" channel="A+">
    <title lang="nl">Pod et Marichou</title>
    <category lang="nl">eigentijds drama</category>
    <country lang="nl">SN</country>
  </programme>
  <programme start="20200601140100 +0000" stop="20200601142300 +0000" channel="A+">
    <title lang="nl">Ma famille</title>
    <desc lang="nl">Le vécu de plusieurs familles ivoiriennes, entre palabres et ragots.(n)</desc>
    <credits>
      <actor>Michel Gohou</actor>
    </credits>
    <category lang="nl">eigentijds drama</category>
    <country lang="nl">CI</country>
  </programme>
  <programme start="20200601142300 +0000" stop="20200601145300 +0000" channel="A+">
    <title lang="nl">Ma famille</title>
    <desc lang="nl">Le vécu de plusieurs familles ivoiriennes, entre palabres et ragots.(n)</desc>
    <credits>
      <actor>Michel Gohou</actor>
    </credits>
    <category lang="nl">eigentijds drama</category>
    <country lang="nl">CI</country>
  </programme>
  <programme start="20200601145300 +0000" stop="20200601153800 +0000" channel="A+">
    <title lang="nl">Celia</title>
    <category lang="nl">eigentijds drama</category>
  </programme>
  <programme start="20200601153800 +0000" stop="20200601160100 +0000" channel="A+">
    <title lang="nl">Sumu</title>
    <desc lang="nl">Série dramatique.(n)</desc>
    <category lang="nl">eigentijds drama</category>
  </programme>
  <programme start="20200601160100 +0000" stop="20200601162500 +0000" channel="A+">
    <title lang="nl">Sumu</title>
    <desc lang="nl">Série dramatique.(n)</desc>
    <category lang="nl">eigentijds drama</category>
  </programme>
  <programme start="20200601162500 +0000" stop="20200601165100 +0000" channel="A+">
    <title lang="nl">Pod et Marichou</title>
    <category lang="nl">eigentijds drama</category>
    <country lang="nl">SN</country>
  </programme>
  <programme start="20200601165100 +0000" stop="20200601172600 +0000" channel="A+">
    <title lang="nl">Pod et Marichou</title>
    <category lang="nl">eigentijds drama</category>
    <country lang="nl">SN</country>
  </programme>
  <programme start="20200601172600 +0000" stop="20200601175600 +0000" channel="A+">
    <title lang="nl">Ma famille</title>
    <desc lang="nl">Le vécu de plusieurs familles ivoiriennes, entre palabres et ragots.(n)</desc>
    <credits>
      <actor>Michel Gohou</actor>
    </credits>
    <category lang="nl">eigentijds drama</category>
    <country lang="nl">CI</country>
  </programme>
  <programme start="20200601175600 +0000" stop="20200601184000 +0000" channel="A+">
    <title lang="nl">Celia</title>
    <category lang="nl">eigentijds drama</category>
  </programme>
  <programme start="20200601184000 +0000" stop="20200601184300 +0000" channel="A+">
    <title lang="nl">Clips</title>
    <sub-title lang="nl">Pas fatigue</sub-title>
    <category lang="nl">Muziek</category>
    <icon src="https://cache.ps.yelo.prd.telenet-ops.be/yposter/images/MMImages/28454686.jpg" />
    <episode-num system="onscreen">E9999</episode-num>
  </programme>
  <programme start="20200601184300 +0000" stop="20200601185000 +0000" channel="A+">
    <title lang="nl">L'heure africaine</title>
    <desc lang="nl">Decothey et ses amis croquent avec beaucoup d'humour la mauvaise habitude du retard.(n)</desc>
    <category lang="nl">Algemene non-fictie</category>
  </programme>
  <programme start="20200601185000 +0000" stop="20200601191200 +0000" channel="A+">
    <title lang="nl">Sumu</title>
    <desc lang="nl">Série dramatique.(n)</desc>
    <category lang="nl">eigentijds drama</category>
  </programme>
  <programme start="20200601191200 +0000" stop="20200601194000 +0000" channel="A+">
    <title lang="nl">Sumu</title>
    <desc lang="nl">Série dramatique.(n)</desc>
    <category lang="nl">eigentijds drama</category>
  </programme>
  <programme start="20200601194000 +0000" stop="20200601200500 +0000" channel="A+">
    <title lang="nl">Pod et Marichou</title>
    <category lang="nl">eigentijds drama</category>
    <country lang="nl">SN</country>
  </programme>
  <programme start="20200601200500 +0000" stop="20200601204000 +0000" channel="A+">
    <title lang="nl">Pod et Marichou</title>
    <category lang="nl">eigentijds drama</category>
    <country lang="nl">SN</country>
  </programme>
  <programme start="20200601204000 +0000" stop="20200601210200 +0000" channel="A+">
    <title lang="nl">Ma famille</title>
    <desc lang="nl">Le vécu de plusieurs familles ivoiriennes, entre palabres et ragots.(n)</desc>
    <credits>
      <actor>Michel Gohou</actor>
    </credits>
    <category lang="nl">eigentijds drama</category>
    <country lang="nl">CI</country>
  </programme>
  <programme start="20200601210200 +0000" stop="20200601213200 +0000" channel="A+">
    <title lang="nl">Ma famille</title>
    <desc lang="nl">Le vécu de plusieurs familles ivoiriennes, entre palabres et ragots.(n)</desc>
    <credits>
      <actor>Michel Gohou</actor>
    </credits>
    <category lang="nl">eigentijds drama</category>
    <country lang="nl">CI</country>
  </programme>
  <programme start="20200601213200 +0000" stop="20200601221600 +0000" channel="A+">
    <title lang="nl">Celia</title>
    <category lang="nl">eigentijds drama</category>
  </programme>
  <programme start="20200601221600 +0000" stop="20200601223900 +0000" channel="A+">
    <title lang="nl">Sumu</title>
    <desc lang="nl">Série dramatique.(n)</desc>
    <category lang="nl">eigentijds drama</category>
  </programme>
  <programme start="20200601223900 +0000" stop="20200601230200 +0000" channel="A+">
    <title lang="nl">Sumu</title>
    <desc lang="nl">Série dramatique.(n)</desc>
    <category lang="nl">eigentijds drama</category>
  </programme>
  <programme start="20200601230200 +0000" stop="20200601232800 +0000" channel="A+">
    <title lang="nl">Pod et Marichou</title>
    <category lang="nl">eigentijds drama</category>
    <country lang="nl">SN</country>
  </programme>
  <programme start="20200601232800 +0000" stop="20200602000300 +0000" channel="A+">
    <title lang="nl">Pod et Marichou</title>
    <category lang="nl">eigentijds drama</category>
    <country lang="nl">SN</country>
  </programme>
  <programme start="20200530030000 +0000" stop="20200530051500 +0000" channel="Nollywood TV">
    <title lang="nl">Quand l'amour revient</title>
    <desc lang="nl">Film sentimental.(n)</desc>
    <credits>
      <actor>Paul Sambo</actor>
    </credits>
    <category lang="nl">Proprietary</category>
    <icon src="https://cache.ps.yelo.prd.telenet-ops.be/yposter/images/MMImages/28253261.jpg" />
  </programme>
  <programme start="20200530051500 +0000" stop="20200530070000 +0000" channel="Nollywood TV">
    <title lang="nl">Le chaos</title>
    <desc lang="nl">Drame.(n)</desc>
    <credits>
      <actor>Enado Odigie</actor>
    </credits>
    <category lang="nl">Proprietary</category>
    <icon src="https://cache.ps.yelo.prd.telenet-ops.be/yposter/images/MMImages/30600607.jpg" />
  </programme>
  <programme start="20200530070000 +0000" stop="20200530080000 +0000" channel="Nollywood TV">
    <title lang="nl">Programme voyance</title>
    <desc lang="nl">Voyance.(n)</desc>
    <category lang="nl">Algemene non-fictie</category>
  </programme>
  <programme start="20200530080000 +0000" stop="20200530110000 +0000" channel="Nollywood TV">
    <title lang="nl">L'autre femme</title>
    <desc lang="nl">Drame.(n)</desc>
    <credits>
      <actor>Esther Audu</actor>
    </credits>
    <category lang="nl">Proprietary</category>
    <icon src="https://cache.ps.yelo.prd.telenet-ops.be/yposter/images/MMImages/30600606.jpg" />
  </programme>
  <programme start="20200530110000 +0000" stop="20200530113000 +0000" channel="Nollywood TV">
    <title lang="nl">L'enver du décor</title>
    <desc lang="nl">Lola est une belle jeune femme passionnée de cinéma qui décide de tout plaquer pour réaliser son rêve.(n)</desc>
    <credits>
      <actor>Diana Yekinni</actor>
    </credits>
    <category lang="nl">eigentijds drama</category>
  </programme>
  <programme start="20200530113000 +0000" stop="20200530120000 +0000" channel="Nollywood TV">
    <title lang="nl">L'enver du décor</title>
    <desc lang="nl">Lola est une belle jeune femme passionnée de cinéma qui décide de tout plaquer pour réaliser son rêve.(n)</desc>
    <credits>
      <actor>Diana Yekinni</actor>
    </credits>
    <category lang="nl">eigentijds drama</category>
  </programme>
  <programme start="20200530120000 +0000" stop="20200530133500 +0000" channel="Nollywood TV">
    <title lang="nl">Les compères</title>
    <desc lang="nl">Linus et Chikioke mettent au point un plan audacieux pour devenir riches aux dépens de leur patron trop gentil.(n)</desc>
    <credits>
      <actor>Alex Ayalogu</actor>
    </credits>
    <category lang="nl">Proprietary</category>
    <icon src="https://cache.ps.yelo.prd.telenet-ops.be/yposter/images/MMImages/28253261.jpg" />
  </programme>
  <programme start="20200530133500 +0000" stop="20200530150000 +0000" channel="Nollywood TV">
    <title lang="nl">Amour au temps des taxi moto</title>
    <desc lang="nl">Film sentimental.(n)</desc>
    <credits>
      <actor>Kelechi Udegbe</actor>
    </credits>
    <category lang="nl">Proprietary</category>
    <icon src="https://cache.ps.yelo.prd.telenet-ops.be/yposter/images/MMImages/30600607.jpg" />
  </programme>
  <programme start="20200530150000 +0000" stop="20200530163000 +0000" channel="Nollywood TV">
    <title lang="nl">La bataille des voisines</title>
    <desc lang="nl">Drame.(n)</desc>
    <credits>
      <actor>Uzor Arukwe</actor>
    </credits>
    <category lang="nl">Proprietary</category>
    <icon src="https://cache.ps.yelo.prd.telenet-ops.be/yposter/images/MMImages/30600606.jpg" />
  </programme>
  <programme start="20200530163000 +0000" stop="20200530180000 +0000" channel="Nollywood TV">
    <title lang="nl">Manipulation</title>
    <credits>
      <actor>Mary Lazarus</actor>
    </credits>
    <category lang="nl">Proprietary</category>
    <icon src="https://cache.ps.yelo.prd.telenet-ops.be/yposter/images/MMImages/28253261.jpg" />
  </programme>
  <programme start="20200530180000 +0000" stop="20200530183000 +0000" channel="Nollywood TV">
    <title lang="nl">Le journal de Jenifa</title>
    <desc lang="nl">Suliat, une coiffeuse de village, débarque en ville pour tenter de rentrer à l?université? Sa nouvelle vie en ville ne sera pas de tout repos.(n)</desc>
    <credits>
      <actor>Funke Akindele</actor>
    </credits>
    <category lang="nl">eigentijds drama</category>
  </programme>
  <programme start="20200530183000 +0000" stop="20200530190000 +0000" channel="Nollywood TV">
    <title lang="nl">Le journal de Jenifa</title>
    <desc lang="nl">Suliat, une coiffeuse de village, débarque en ville pour tenter de rentrer à l?université? Sa nouvelle vie en ville ne sera pas de tout repos.(n)</desc>
    <credits>
      <actor>Funke Akindele</actor>
    </credits>
    <category lang="nl">eigentijds drama</category>
  </programme>
  <programme start="20200530190000 +0000" stop="20200530210500 +0000" channel="Nollywood TV">
    <title lang="nl">Evil Deeds</title>
    <category lang="nl">Proprietary</category>
  </programme>
  <programme start="20200530210500 +0000" stop="20200530224000 +0000" channel="Nollywood TV">
    <title lang="nl">L'intrus</title>
    <desc lang="nl">Drame.(n)</desc>
    <credits>
      <actor>Ruth Kadiri</actor>
    </credits>
    <category lang="nl">Proprietary</category>
    <icon src="https://cache.ps.yelo.prd.telenet-ops.be/yposter/images/MMImages/30600607.jpg" />
  </programme>
  <programme start="20200530224000 +0000" stop="20200530233500 +0000" channel="Nollywood TV">
    <title lang="nl">Programme voyance</title>
    <desc lang="nl">Voyance.(n)</desc>
    <category lang="nl">Algemene non-fictie</category>
  </programme>
  <programme start="20200530233500 +0000" stop="20200531013000 +0000" channel="Nollywood TV">
    <title lang="nl">Non coupable</title>
    <desc lang="nl">Drame.(n)</desc>
    <credits>
      <actor>Mike Godson</actor>
    </credits>
    <category lang="nl">Proprietary</category>
    <icon src="https://cache.ps.yelo.prd.telenet-ops.be/yposter/images/MMImages/30600606.jpg" />
  </programme>
  <programme start="20200531013000 +0000" stop="20200531053000 +0000" channel="Nollywood TV">
    <title lang="nl">Unmasked</title>
    <desc lang="nl">Als er op Halloween wordt aangebeld, verwacht Doreen Erbert kinderen die snoep willen, maar in plaats daarvan dringt een gemaskerde moordenaar het huis binnen. Wie is de dader?(n)</desc>
    <category lang="nl">Algemene non-fictie</category>
    <icon src="https://cache.ps.yelo.prd.telenet-ops.be/yposter/images/MMImages/139191445.jpg" />
    <country lang="nl">US</country>
    <episode-num system="onscreen">S1 E9999</episode-num>
  </programme>
  <programme start="20200531053000 +0000" stop="20200531070000 +0000" channel="Nollywood TV">
    <title lang="nl">In Justice</title>
    <category lang="nl">Proprietary</category>
    <icon src="https://cache.ps.yelo.prd.telenet-ops.be/yposter/images/MMImages/28560450.jpg" />
  </programme>
  <programme start="20200531070000 +0000" stop="20200531075500 +0000" channel="Nollywood TV">
    <title lang="nl">Programme voyance</title>
    <desc lang="nl">Voyance.(n)</desc>
    <category lang="nl">Algemene non-fictie</category>
  </programme>
  <programme start="20200531075500 +0000" stop="20200531110000 +0000" channel="Nollywood TV">
    <title lang="nl">Instable</title>
    <desc lang="nl">Drame.(n)</desc>
    <credits>
      <actor>Yvonne Nelson</actor>
    </credits>
    <category lang="nl">Proprietary</category>
    <icon src="https://cache.ps.yelo.prd.telenet-ops.be/yposter/images/MMImages/28253261.jpg" />
  </programme>
  <programme start="20200531110000 +0000" stop="20200531113000 +0000" channel="Nollywood TV">
    <title lang="nl">L'enver du décor</title>
    <desc lang="nl">Lola est une belle jeune femme passionnée de cinéma qui décide de tout plaquer pour réaliser son rêve.(n)</desc>
    <credits>
      <actor>Diana Yekinni</actor>
    </credits>
    <category lang="nl">eigentijds drama</category>
  </programme>
  <programme start="20200531113000 +0000" stop="20200531120000 +0000" channel="Nollywood TV">
    <title lang="nl">Le journal de Jenifa</title>
    <desc lang="nl">Suliat, une coiffeuse de village, débarque en ville pour tenter de rentrer à l?université? Sa nouvelle vie en ville ne sera pas de tout repos.(n)</desc>
    <credits>
      <actor>Funke Akindele</actor>
    </credits>
    <category lang="nl">eigentijds drama</category>
  </programme>
  <programme start="20200531120000 +0000" stop="20200531140000 +0000" channel="Nollywood TV">
    <title lang="nl">Le fiancé</title>
    <desc lang="nl">Film sentimental.(n)</desc>
    <credits>
      <actor>Paul Sambo</actor>
    </credits>
    <category lang="nl">Proprietary</category>
    <icon src="https://cache.ps.yelo.prd.telenet-ops.be/yposter/images/MMImages/30600607.jpg" />
  </programme>
  <programme start="20200531140000 +0000" stop="20200531155500 +0000" channel="Nollywood TV">
    <title lang="nl">Les compères</title>
    <desc lang="nl">Linus et Chikioke mettent au point un plan audacieux pour devenir riches aux dépens de leur patron trop gentil.(n)</desc>
    <credits>
      <actor>Alex Ayalogu</actor>
    </credits>
    <category lang="nl">Proprietary</category>
    <icon src="https://cache.ps.yelo.prd.telenet-ops.be/yposter/images/MMImages/28253261.jpg" />
  </programme>
  <programme start="20200531155500 +0000" stop="20200531180000 +0000" channel="Nollywood TV">
    <title lang="nl">Épreuve familiale</title>
    <desc lang="nl">Drame.(n)</desc>
    <credits>
      <actor>Rita Dominic</actor>
    </credits>
    <category lang="nl">Proprietary</category>
    <icon src="https://cache.ps.yelo.prd.telenet-ops.be/yposter/images/MMImages/30600606.jpg" />
  </programme>
  <programme start="20200531180000 +0000" stop="20200531183000 +0000" channel="Nollywood TV">
    <title lang="nl">Le journal de Jenifa</title>
    <desc lang="nl">Suliat, une coiffeuse de village, débarque en ville pour tenter de rentrer à l?université? Sa nouvelle vie en ville ne sera pas de tout repos.(n)</desc>
    <credits>
      <actor>Funke Akindele</actor>
    </credits>
    <category lang="nl">eigentijds drama</category>
  </programme>
  <programme start="20200531183000 +0000" stop="20200531190000 +0000" channel="Nollywood TV">
    <title lang="nl">Le journal de Jenifa</title>
    <desc lang="nl">Suliat, une coiffeuse de village, débarque en ville pour tenter de rentrer à l?université? Sa nouvelle vie en ville ne sera pas de tout repos.(n)</desc>
    <credits>
      <actor>Funke Akindele</actor>
    </credits>
    <category lang="nl">eigentijds drama</category>
  </programme>
  <programme start="20200531190000 +0000" stop="20200531203500 +0000" channel="Nollywood TV">
    <title lang="nl">La promotion</title>
    <desc lang="nl">Drame.(n)</desc>
    <credits>
      <actor>Femi Branch</actor>
    </credits>
    <category lang="nl">Proprietary</category>
    <icon src="https://cache.ps.yelo.prd.telenet-ops.be/yposter/images/MMImages/28253261.jpg" />
  </programme>
  <programme start="20200531203500 +0000" stop="20200531220500 +0000" channel="Nollywood TV">
    <title lang="nl">Le fiancé</title>
    <desc lang="nl">Film sentimental.(n)</desc>
    <credits>
      <actor>Paul Sambo</actor>
    </credits>
    <category lang="nl">Proprietary</category>
    <icon src="https://cache.ps.yelo.prd.telenet-ops.be/yposter/images/MMImages/30600607.jpg" />
  </programme>
  <programme start="20200531220500 +0000" stop="20200601002000 +0000" channel="Nollywood TV">
    <title lang="nl">Ma promise</title>
    <desc lang="nl">Film sentimental.(n)</desc>
    <credits>
      <actor>Okey Uzoeshi</actor>
    </credits>
    <category lang="nl">Proprietary</category>
    <icon src="https://cache.ps.yelo.prd.telenet-ops.be/yposter/images/MMImages/30600607.jpg" />
  </programme>
  <programme start="20200601002000 +0000" stop="20200601011000 +0000" channel="Nollywood TV">
    <title lang="nl">Programme voyance</title>
    <desc lang="nl">Voyance.(n)</desc>
    <category lang="nl">Algemene non-fictie</category>
  </programme>
  <programme start="20200601011000 +0000" stop="20200601024500 +0000" channel="Nollywood TV">
    <title lang="nl">Lettre en sang</title>
    <desc lang="nl">Drame.(n)</desc>
    <credits>
      <actor>Stan Nze</actor>
    </credits>
    <category lang="nl">Proprietary</category>
    <icon src="https://cache.ps.yelo.prd.telenet-ops.be/yposter/images/MMImages/30600606.jpg" />
  </programme>
  <programme start="20200601024500 +0000" stop="20200601034000 +0000" channel="Nollywood TV">
    <title lang="nl">Instable</title>
    <desc lang="nl">Drame.(n)</desc>
    <credits>
      <actor>Yvonne Nelson</actor>
    </credits>
    <category lang="nl">Proprietary</category>
    <icon src="https://cache.ps.yelo.prd.telenet-ops.be/yposter/images/MMImages/28253261.jpg" />
  </programme>
  <programme start="20200601034000 +0000" stop="20200601045500 +0000" channel="Nollywood TV">
    <title lang="nl">Lettre en sang</title>
    <desc lang="nl">Drame.(n)</desc>
    <credits>
      <actor>Stan Nze</actor>
    </credits>
    <category lang="nl">Proprietary</category>
    <icon src="https://cache.ps.yelo.prd.telenet-ops.be/yposter/images/MMImages/30600606.jpg" />
  </programme>
  <programme start="20200601045500 +0000" stop="20200601070000 +0000" channel="Nollywood TV">
    <title lang="nl">Par tous les moyens</title>
    <desc lang="nl">Drame.(n)</desc>
    <credits>
      <actor>Maureen Okpoko</actor>
    </credits>
    <category lang="nl">Proprietary</category>
    <icon src="https://cache.ps.yelo.prd.telenet-ops.be/yposter/images/MMImages/28253261.jpg" />
  </programme>
  <programme start="20200601070000 +0000" stop="20200601080000 +0000" channel="Nollywood TV">
    <title lang="nl">Programme voyance</title>
    <desc lang="nl">Voyance.(n)</desc>
    <category lang="nl">Algemene non-fictie</category>
  </programme>
  <programme start="20200601080000 +0000" stop="20200601110000 +0000" channel="Nollywood TV">
    <title lang="nl">Lettre en sang</title>
    <desc lang="nl">Drame.(n)</desc>
    <credits>
      <actor>Stan Nze</actor>
    </credits>
    <category lang="nl">Proprietary</category>
    <icon src="https://cache.ps.yelo.prd.telenet-ops.be/yposter/images/MMImages/30600606.jpg" />
  </programme>
  <programme start="20200601110000 +0000" stop="20200601113000 +0000" channel="Nollywood TV">
    <title lang="nl">Le journal de Jenifa</title>
    <desc lang="nl">Suliat, une coiffeuse de village, débarque en ville pour tenter de rentrer à l?université? Sa nouvelle vie en ville ne sera pas de tout repos.(n)</desc>
    <credits>
      <actor>Funke Akindele</actor>
    </credits>
    <category lang="nl">eigentijds drama</category>
  </programme>
  <programme start="20200601113000 +0000" stop="20200601120000 +0000" channel="Nollywood TV">
    <title lang="nl">Le journal de Jenifa</title>
    <desc lang="nl">Suliat, une coiffeuse de village, débarque en ville pour tenter de rentrer à l?université? Sa nouvelle vie en ville ne sera pas de tout repos.(n)</desc>
    <credits>
      <actor>Funke Akindele</actor>
    </credits>
    <category lang="nl">eigentijds drama</category>
  </programme>
  <programme start="20200601120000 +0000" stop="20200601140000 +0000" channel="Nollywood TV">
    <title lang="nl">Instable</title>
    <desc lang="nl">Drame.(n)</desc>
    <credits>
      <actor>Yvonne Nelson</actor>
    </credits>
    <category lang="nl">Proprietary</category>
    <icon src="https://cache.ps.yelo.prd.telenet-ops.be/yposter/images/MMImages/28253261.jpg" />
  </programme>
  <programme start="20200601140000 +0000" stop="20200601160000 +0000" channel="Nollywood TV">
    <title lang="nl">Recherche du bonheur</title>
    <desc lang="nl">Drame.(n)</desc>
    <credits>
      <actor>Bimbo Ademoye</actor>
    </credits>
    <category lang="nl">Proprietary</category>
    <icon src="https://cache.ps.yelo.prd.telenet-ops.be/yposter/images/MMImages/30600607.jpg" />
  </programme>
  <programme start="20200601160000 +0000" stop="20200601180000 +0000" channel="Nollywood TV">
    <title lang="nl">Je m'appelle Kadi</title>
    <desc lang="nl">Drame.(n)</desc>
    <credits>
      <actor>Vincent Opurum</actor>
    </credits>
    <category lang="nl">Proprietary</category>
    <icon src="https://cache.ps.yelo.prd.telenet-ops.be/yposter/images/MMImages/30600606.jpg" />
  </programme>
  <programme start="20200601180000 +0000" stop="20200601183000 +0000" channel="Nollywood TV">
    <title lang="nl">Le journal de Jenifa</title>
    <desc lang="nl">Suliat, une coiffeuse de village, débarque en ville pour tenter de rentrer à l?université? Sa nouvelle vie en ville ne sera pas de tout repos.(n)</desc>
    <credits>
      <actor>Funke Akindele</actor>
    </credits>
    <category lang="nl">eigentijds drama</category>
  </programme>
  <programme start="20200601183000 +0000" stop="20200601190000 +0000" channel="Nollywood TV">
    <title lang="nl">Le journal de Jenifa</title>
    <desc lang="nl">Suliat, une coiffeuse de village, débarque en ville pour tenter de rentrer à l?université? Sa nouvelle vie en ville ne sera pas de tout repos.(n)</desc>
    <credits>
      <actor>Funke Akindele</actor>
    </credits>
    <category lang="nl">eigentijds drama</category>
  </programme>
  <programme start="20200601190000 +0000" stop="20200601205000 +0000" channel="Nollywood TV">
    <title lang="nl">La femme de ma vie</title>
    <credits>
      <actor>Tina Mba</actor>
    </credits>
    <category lang="nl">Proprietary</category>
    <icon src="https://cache.ps.yelo.prd.telenet-ops.be/yposter/images/MMImages/28253261.jpg" />
  </programme>
  <programme start="20200601205000 +0000" stop="20200601225500 +0000" channel="Nollywood TV">
    <title lang="nl">Evil Deeds</title>
    <category lang="nl">Proprietary</category>
  </programme>
  <programme start="20200601225500 +0000" stop="20200601235000 +0000" channel="Nollywood TV">
    <title lang="nl">Programme voyance</title>
    <desc lang="nl">Voyance.(n)</desc>
    <category lang="nl">Algemene non-fictie</category>
  </programme>
  <programme start="20200601235000 +0000" stop="20200602011500 +0000" channel="Nollywood TV">
    <title lang="nl">Manipulation</title>
    <credits>
      <actor>Mary Lazarus</actor>
    </credits>
    <category lang="nl">Proprietary</category>
    <icon src="https://cache.ps.yelo.prd.telenet-ops.be/yposter/images/MMImages/28253261.jpg" />
  </programme>
</tv>